{"open_content": "no", "classification": "Vessels", "name": "Square Bottle", "maker": "Unknown", "description": "Square Bottle; Unknown; Eastern Mediterranean; 2nd - 3rd century; Glass; 18 cm (7 1/16 in.); 71.AF.79; J. Paul Getty Museum, Los Angeles, California", "dimensions": "18 cm (7 1/16 in.)", "object_number": "71.AF.79", "title": "Square Bottle", "department": "Antiquities", "culture": "Roman (Syrian)", "medium": "Glass", "on_view": "yes", "keywords": "Getty Museum collections, artworks, art works, art history, video, interpretation of art, acquisitions, artists, Getty art, collections Getty, collezioni Getty, colecciones Getty, Sammlung Getty, Getty exhibits, Getty current exhibitions, Getty Museum exhibits, los angeles collections, antiquities, decorative arts, sculpture, manuscripts, photography, paintings, drawings", "date": "2nd - 3rd century", "place_created": "Eastern Mediterranean", "object_type": "Pitcher"}