{"description": "The Penitent Magdalene; Titian (Tiziano Vecellio) (Italian, about 1487 - 1576); 1555 - 1565; Oil on canvas; 108.3 × 94.3 cm (42 5/8 × 37 1/8 in.); 56.PA.1; J. Paul Getty Museum, Los Angeles, California", "image": "http://www.getty.edu/museum/media/images/web/enlarge/00053601.jpg", "date": "1555 - 1565", "canonical_url": "http://www.getty.edu/art/collection/objects/519", "image_full": "http://www.getty.edu/museum/media/images/web/download/00053601.jpg", "culture": "Italian", "maker": "Titian (Tiziano Vecellio)", "medium": "Oil on canvas", "classification": "Paintings", "name": "The Penitent Magdalene", "keywords": "Getty Museum collections, artworks, art works, art history, video, interpretation of art, acquisitions, artists, Getty art, collections Getty, collezioni Getty, colecciones Getty, Sammlung Getty, Getty exhibits, Getty current exhibitions, Getty Museum exhibits, los angeles collections, antiquities, decorative arts, sculpture, manuscripts, photography, paintings, drawings", "location": "gc", "object_number": "56.PA.1", "open_content": "yes", "title": "The Penitent Magdalene", "department": "Paintings", "thumbimage": "http://www.getty.edu/museum/media/images/web/thumbnail/00053601.jpg", "dimensions": "108.3 × 94.3 cm (42 5/8 × 37 1/8 in.)", "on_view": "yes", "object_type": "Painting"}