{"maker": "Unknown", "title": "Adze", "description": "Adze; Unknown; Roman Empire; 1st century; Iron; 20.3 cm (8 in.); 81.AI.18; J. Paul Getty Museum, Los Angeles, California", "on_view": "yes", "open_content": "no", "object_number": "81.AI.18", "canonical_url": "http://www.getty.edu/art/collection/objects/9391", "keywords": "Getty Museum collections, artworks, art works, art history, video, interpretation of art, acquisitions, artists, Getty art, collections Getty, collezioni Getty, colecciones Getty, Sammlung Getty, Getty exhibits, Getty current exhibitions, Getty Museum exhibits, los angeles collections, antiquities, decorative arts, sculpture, manuscripts, photography, paintings, drawings", "name": "Adze", "classification": "Implements", "culture": "Roman", "date": "1st century", "department": "Antiquities", "dimensions": "20.3 cm (8 in.)", "place_created": "Roman Empire", "object_type": "Implement", "medium": "Iron"}