{"maker": "Attributed to Lucien-François Feuchère", "thumbimage": "http://www.getty.edu/museum/media/images/web/thumbnail/00615201.jpg", "title": "Pair of Standing Candelabra", "on_view": "yes", "open_content": "yes", "object_number": "71.DF.99", "canonical_url": "http://www.getty.edu/art/collection/objects/5436", "image_full": "http://www.getty.edu/museum/media/images/web/download/00615201.jpg", "location": "gc", "keywords": "Getty Museum collections, artworks, art works, art history, video, interpretation of art, acquisitions, artists, Getty art, collections Getty, collezioni Getty, colecciones Getty, Sammlung Getty, Getty exhibits, Getty current exhibitions, Getty Museum exhibits, los angeles collections, antiquities, decorative arts, sculpture, manuscripts, photography, paintings, drawings", "name": "Pair of Standing Candelabra", "classification": "Decorative Arts", "culture": "French", "image": "http://www.getty.edu/museum/media/images/web/enlarge/00615201.jpg", "date": "about 1784 - 1786", "department": "Sculpture & Decorative Arts", "description": "Pair of Standing Candelabra; Attributed to Lucien-François Feuchère (French, about 1750 - 1828); Paris, France; about 1784 - 1786; Blued metal; gilt bronze; 71.DF.99; J. Paul Getty Museum, Los Angeles, California", "place_created": "Paris, France", "object_type": "Candelabrum", "medium": "Blued metal; gilt bronze"}