{"open_content": "no", "classification": "Manuscripts", "name": "Leaf from Histoire ancienne jusqu'à César (fol. 84)", "maker": "First Master of the Bible historiale of Jean de Berry, Unknown", "description": "Leaf from Histoire ancienne jusqu'à César (fol. 84); First Master of the Bible historiale of Jean de Berry (French, active about 1390 - about 1400), Unknown; Paris, France; about 1390 - 1400; Tempera colors, colored washes, gold leaf, and ink on parchment; Leaf: 38.3 x 29.8 cm (15 1/16 x 11 3/4 in.); Ms. Ludwig XIII 3 (3); J. Paul Getty Museum, Los Angeles, California", "dimensions": "Leaf: 38.3 x 29.8 cm (15 1/16 x 11 3/4 in.)", "object_number": "Ms. Ludwig XIII 3 (3)", "title": "Leaf from Histoire ancienne jusqu'à César (fol. 84)", "department": "Manuscripts", "culture": "French", "medium": "Tempera colors, colored washes, gold leaf, and ink on parchment", "on_view": "yes", "keywords": "Getty Museum collections, artworks, art works, art history, video, interpretation of art, acquisitions, artists, Getty art, collections Getty, collezioni Getty, colecciones Getty, Sammlung Getty, Getty exhibits, Getty current exhibitions, Getty Museum exhibits, los angeles collections, antiquities, decorative arts, sculpture, manuscripts, photography, paintings, drawings", "date": "about 1390 - 1400", "place_created": "Paris, France", "object_type": "Detached leaf"}