{"open_content": "yes", "classification": "Drawings", "name": "Study of an Angel and of Drapery", "maker": "Innocenzo da Imola", "description": "Study of an Angel and of Drapery; Innocenzo da Imola (Italian, 1485 - 1550); Italy; about 1520; Black chalk and brown wash, with white gouache heightening on brown tinted paper, with corners removed; 25.7 × 19.5 cm (10 1/8 × 7 11/16 in.); 85.GG.289; J. Paul Getty Museum, Los Angeles, California", "image_full": "http://www.getty.edu/museum/media/images/web/download/00013501.jpg", "dimensions": "25.7 × 19.5 cm (10 1/8 × 7 11/16 in.)", "object_number": "85.GG.289", "title": "Study of an Angel and of Drapery", "department": "Drawings", "image": "http://www.getty.edu/museum/media/images/web/enlarge/00013501.jpg", "culture": "Italian", "medium": "Black chalk and brown wash, with white gouache heightening on brown tinted paper, with corners removed", "on_view": "yes", "keywords": "Getty Museum collections, artworks, art works, art history, video, interpretation of art, acquisitions, artists, Getty art, collections Getty, collezioni Getty, colecciones Getty, Sammlung Getty, Getty exhibits, Getty current exhibitions, Getty Museum exhibits, los angeles collections, antiquities, decorative arts, sculpture, manuscripts, photography, paintings, drawings", "thumbimage": "http://www.getty.edu/museum/media/images/web/thumbnail/00013501.jpg", "date": "about 1520", "place_created": "Italy", "object_type": "Drawing"}