{"open_content": "yes", "classification": "Manuscripts", "name": "Two Miniatures, Possibly from a Manuscript", "maker": "Master of St. Veronica", "description": "Two Miniatures, Possibly from a Manuscript; Master of St. Veronica (German, active about 1395 - 1415); Cologne, Germany; about 1400 - 1410; Tempera colors, gold paint, and gold leaf on parchment; Ms. Ludwig Folia 2; J. Paul Getty Museum, Los Angeles, California", "image_full": "http://www.getty.edu/museum/media/images/web/download/11231401.jpg", "object_number": "Ms. Ludwig Folia 2", "title": "Two Miniatures, Possibly from a Manuscript", "department": "Manuscripts", "image": "http://www.getty.edu/museum/media/images/web/enlarge/11231401.jpg", "culture": "German", "medium": "Tempera colors, gold paint, and gold leaf on parchment", "on_view": "yes", "keywords": "Getty Museum collections, artworks, art works, art history, video, interpretation of art, acquisitions, artists, Getty art, collections Getty, collezioni Getty, colecciones Getty, Sammlung Getty, Getty exhibits, Getty current exhibitions, Getty Museum exhibits, los angeles collections, antiquities, decorative arts, sculpture, manuscripts, photography, paintings, drawings", "thumbimage": "http://www.getty.edu/museum/media/images/web/thumbnail/11231401.jpg", "date": "about 1400 - 1410", "place_created": "Cologne, Germany", "object_type": "Detached leaf"}