{"open_content": "yes", "classification": "Drawings", "name": "Vases, Furniture and Objects Discovered at Herculaneum", "maker": "Pierre-Adrien Pâris", "description": "Vases, Furniture and Objects Discovered at Herculaneum; Pierre-Adrien Pâris (French, 1745 - 1819); France; 1777; Pen and black ink, watercolor; 22.9 x 37 cm (9 x 14 9/16 in.); 88.GA.26; J. Paul Getty Museum, Los Angeles, California", "image_full": "http://www.getty.edu/museum/media/images/web/download/00024201.jpg", "dimensions": "22.9 x 37 cm (9 x 14 9/16 in.)", "object_number": "88.GA.26", "title": "Vases, Furniture and Objects Discovered at Herculaneum", "department": "Drawings", "image": "http://www.getty.edu/museum/media/images/web/enlarge/00024201.jpg", "culture": "French", "medium": "Pen and black ink, watercolor", "on_view": "yes", "keywords": "Getty Museum collections, artworks, art works, art history, video, interpretation of art, acquisitions, artists, Getty art, collections Getty, collezioni Getty, colecciones Getty, Sammlung Getty, Getty exhibits, Getty current exhibitions, Getty Museum exhibits, los angeles collections, antiquities, decorative arts, sculpture, manuscripts, photography, paintings, drawings", "thumbimage": "http://www.getty.edu/museum/media/images/web/thumbnail/00024201.jpg", "date": "1777", "place_created": "France", "object_type": "Drawing"}