{"maker": "Simon Gallien", "thumbimage": "http://www.getty.edu/museum/media/images/web/thumbnail/00671201.jpg", "title": "Pair of Sugar Casters", "on_view": "yes", "open_content": "yes", "object_number": "84.DG.744", "canonical_url": "http://www.getty.edu/art/collection/objects/5852", "image_full": "http://www.getty.edu/museum/media/images/web/download/00671201.jpg", "location": "gc", "keywords": "Getty Museum collections, artworks, art works, art history, video, interpretation of art, acquisitions, artists, Getty art, collections Getty, collezioni Getty, colecciones Getty, Sammlung Getty, Getty exhibits, Getty current exhibitions, Getty Museum exhibits, los angeles collections, antiquities, decorative arts, sculpture, manuscripts, photography, paintings, drawings", "name": "Pair of Sugar Casters", "classification": "Decorative Arts", "culture": "French", "image": "http://www.getty.edu/museum/media/images/web/enlarge/00671201.jpg", "date": "1743", "department": "Sculpture & Decorative Arts", "description": "Pair of Sugar Casters; Simon Gallien (French, died 1757, master 1714); Paris, France; 1743; Silver; 84.DG.744; J. Paul Getty Museum, Los Angeles, California", "place_created": "Paris, France", "object_type": "Caster", "medium": "Silver"}