{"open_content": "yes", "classification": "Decorative Arts", "name": "Pair of Firedogs", "maker": "Attributed to Charles Cressent", "description": "Pair of Firedogs; Attributed to Charles Cressent (French, 1685 - 1768, master 1719); Paris, France; about 1735; Gilt bronze; 73.DF.63; J. Paul Getty Museum, Los Angeles, California", "image_full": "http://www.getty.edu/museum/media/images/web/download/00623901.jpg", "object_number": "73.DF.63", "title": "Pair of Firedogs", "department": "Sculpture & Decorative Arts", "image": "http://www.getty.edu/museum/media/images/web/enlarge/00623901.jpg", "culture": "French", "medium": "Gilt bronze", "on_view": "yes", "keywords": "Getty Museum collections, artworks, art works, art history, video, interpretation of art, acquisitions, artists, Getty art, collections Getty, collezioni Getty, colecciones Getty, Sammlung Getty, Getty exhibits, Getty current exhibitions, Getty Museum exhibits, los angeles collections, antiquities, decorative arts, sculpture, manuscripts, photography, paintings, drawings", "thumbimage": "http://www.getty.edu/museum/media/images/web/thumbnail/00623901.jpg", "date": "about 1735", "place_created": "Paris, France", "object_type": "Firedog"}