{"open_content": "no", "classification": "Sculpture", "name": "Cast from a Sicilian Mold", "maker": "Unknown", "description": "Cast from a Sicilian Mold; Unknown; Europe (?); 20th century; Terracotta; 12.2 cm (4 13/16 in.); 78.AK.412; Gift of Malcolm Wiener; J. Paul Getty Museum, Los Angeles, California", "dimensions": "12.2 cm (4 13/16 in.)", "object_number": "78.AK.412", "title": "Cast from a Sicilian Mold", "department": "Antiquities", "culture": "Modern", "medium": "Terracotta", "on_view": "yes", "keywords": "Getty Museum collections, artworks, art works, art history, video, interpretation of art, acquisitions, artists, Getty art, collections Getty, collezioni Getty, colecciones Getty, Sammlung Getty, Getty exhibits, Getty current exhibitions, Getty Museum exhibits, los angeles collections, antiquities, decorative arts, sculpture, manuscripts, photography, paintings, drawings", "date": "20th century", "place_created": "Europe (?)", "object_type": "Female figure"}