{"description": "Votary of Bacchus; Nicolas Poussin (French, 1594 - 1665); about 1640; Pen and brown ink and brown wash; 15.7 x 13.5 cm (6 3/16 x 5 5/16 in.); 86.GG.469; J. Paul Getty Museum, Los Angeles, California", "image": "http://www.getty.edu/museum/media/images/web/enlarge/00016901.jpg", "date": "about 1640", "canonical_url": "http://www.getty.edu/art/collection/objects/168", "image_full": "http://www.getty.edu/museum/media/images/web/download/00016901.jpg", "culture": "French", "maker": "Nicolas Poussin", "medium": "Pen and brown ink and brown wash", "classification": "Drawings", "name": "Votary of Bacchus", "keywords": "Getty Museum collections, artworks, art works, art history, video, interpretation of art, acquisitions, artists, Getty art, collections Getty, collezioni Getty, colecciones Getty, Sammlung Getty, Getty exhibits, Getty current exhibitions, Getty Museum exhibits, los angeles collections, antiquities, decorative arts, sculpture, manuscripts, photography, paintings, drawings", "object_number": "86.GG.469", "open_content": "yes", "title": "Votary of Bacchus", "department": "Drawings", "thumbimage": "http://www.getty.edu/museum/media/images/web/thumbnail/00016901.jpg", "dimensions": "15.7 x 13.5 cm (6 3/16 x 5 5/16 in.)", "on_view": "yes", "object_type": "Drawing"}