{"open_content": "yes", "classification": "Drawings", "name": "A Sailing Boat on a Wide Expanse of Water", "maker": "Rembrandt Harmensz. van Rijn", "description": "A Sailing Boat on a Wide Expanse of Water; Rembrandt Harmensz. van Rijn (Dutch, 1606 - 1669); about 1650; Pen and brown ink and brown wash, on tinted paper; 8.9 x 18.3 cm (3 1/2 x 7 3/16 in.); 85.GA.94; J. Paul Getty Museum, Los Angeles, California", "image_full": "http://www.getty.edu/museum/media/images/web/download/00011601.jpg", "dimensions": "8.9 x 18.3 cm (3 1/2 x 7 3/16 in.)", "object_number": "85.GA.94", "title": "A Sailing Boat on a Wide Expanse of Water", "department": "Drawings", "image": "http://www.getty.edu/museum/media/images/web/enlarge/00011601.jpg", "culture": "Dutch", "medium": "Pen and brown ink and brown wash, on tinted paper", "on_view": "yes", "keywords": "Getty Museum collections, artworks, art works, art history, video, interpretation of art, acquisitions, artists, Getty art, collections Getty, collezioni Getty, colecciones Getty, Sammlung Getty, Getty exhibits, Getty current exhibitions, Getty Museum exhibits, los angeles collections, antiquities, decorative arts, sculpture, manuscripts, photography, paintings, drawings", "thumbimage": "http://www.getty.edu/museum/media/images/web/thumbnail/00011601.jpg", "date": "about 1650", "object_type": "Drawing"}