{"open_content": "no", "classification": "Sculpture", "name": "Head of a Female Attendant from a Grave Naiskos", "maker": "Unknown", "description": "Head of a Female Attendant from a Grave Naiskos; Unknown; Greece (Attica); about 350 B.C.; Pentelic Marble; 21.6 × 17 × 10.5 cm (8 1/2 × 6 11/16 × 4 1/8 in.); 57.AA.14; J. Paul Getty Museum, Los Angeles, California", "dimensions": "21.6 × 17 × 10.5 cm (8 1/2 × 6 11/16 × 4 1/8 in.)", "object_number": "57.AA.14", "title": "Head of a Female Attendant from a Grave Naiskos", "department": "Antiquities", "culture": "Greek", "medium": "Pentelic Marble", "on_view": "yes", "keywords": "Getty Museum collections, artworks, art works, art history, video, interpretation of art, acquisitions, artists, Getty art, collections Getty, collezioni Getty, colecciones Getty, Sammlung Getty, Getty exhibits, Getty current exhibitions, Getty Museum exhibits, los angeles collections, antiquities, decorative arts, sculpture, manuscripts, photography, paintings, drawings", "date": "about 350 B.C.", "place_created": "Greece (Attica)", "object_type": "Relief"}