{"maker": "Unknown", "title": "Girandole", "description": "Girandole; Unknown; Paris, France; about 1730; Gilt bronze; rock crystal; 86.4 x 62.2 x 37.5 cm (34 x 24 1/2 x 14 3/4 in.); 75.DF.53.2; J. Paul Getty Museum, Los Angeles, California", "on_view": "yes", "open_content": "no", "object_number": "75.DF.53.2", "canonical_url": "http://www.getty.edu/art/collection/objects/5589", "location": "gc", "keywords": "Getty Museum collections, artworks, art works, art history, video, interpretation of art, acquisitions, artists, Getty art, collections Getty, collezioni Getty, colecciones Getty, Sammlung Getty, Getty exhibits, Getty current exhibitions, Getty Museum exhibits, los angeles collections, antiquities, decorative arts, sculpture, manuscripts, photography, paintings, drawings", "name": "Girandole", "classification": "Decorative Arts", "culture": "French", "date": "about 1730", "department": "Sculpture & Decorative Arts", "dimensions": "86.4 x 62.2 x 37.5 cm (34 x 24 1/2 x 14 3/4 in.)", "place_created": "Paris, France", "object_type": "Girandole", "medium": "Gilt bronze; rock crystal"}