{"maker": "Unknown", "thumbimage": "http://www.getty.edu/museum/media/images/web/thumbnail/00801401.jpg", "title": "Wall fragment with Siren, Sea Monsters and Niche on Black Ground", "description": "Wall fragment with Siren, Sea Monsters and Niche on Black Ground; Unknown; Boscoreale, Italy; 50 - 79; Fresco; 84 × 64 cm (33 1/16 × 25 3/16 in.); 72.AG.78.6; J. Paul Getty Museum, Los Angeles, California", "on_view": "yes", "open_content": "yes", "object_number": "72.AG.78.6", "canonical_url": "http://www.getty.edu/art/collection/objects/6923", "image_full": "http://www.getty.edu/museum/media/images/web/download/00801401.jpg", "keywords": "Getty Museum collections, artworks, art works, art history, video, interpretation of art, acquisitions, artists, Getty art, collections Getty, collezioni Getty, colecciones Getty, Sammlung Getty, Getty exhibits, Getty current exhibitions, Getty Museum exhibits, los angeles collections, antiquities, decorative arts, sculpture, manuscripts, photography, paintings, drawings", "name": "Wall fragment with Siren, Sea Monsters and Niche on Black Ground", "classification": "Paintings", "culture": "Roman", "image": "http://www.getty.edu/museum/media/images/web/enlarge/00801401.jpg", "date": "50 - 79", "department": "Antiquities", "dimensions": "84 × 64 cm (33 1/16 × 25 3/16 in.)", "place_created": "Boscoreale, Italy", "object_type": "Fresco", "medium": "Fresco"}