{"open_content": "yes", "classification": "Manuscripts", "name": "Initial O: A Prophet", "maker": "Circle of Stefan Lochner", "description": "Initial O: A Prophet; Circle of Stefan Lochner (German, died 1451); Cologne, Germany; about 1450; Gold leaf, tempera, and black ink on parchment; Leaf: 36.7 x 26 cm (14 7/16 x 10 1/4 in.); Ms. Ludwig I 13, fol. 221; J. Paul Getty Museum, Los Angeles, California", "image_full": "http://www.getty.edu/museum/media/images/web/download/00323101.jpg", "dimensions": "Leaf: 36.7 x 26 cm (14 7/16 x 10 1/4 in.)", "object_number": "Ms. Ludwig I 13, fol. 221", "title": "Initial O: A Prophet", "department": "Manuscripts", "image": "http://www.getty.edu/museum/media/images/web/enlarge/00323101.jpg", "culture": "German", "medium": "Gold leaf, tempera, and black ink on parchment", "on_view": "yes", "keywords": "Getty Museum collections, artworks, art works, art history, video, interpretation of art, acquisitions, artists, Getty art, collections Getty, collezioni Getty, colecciones Getty, Sammlung Getty, Getty exhibits, Getty current exhibitions, Getty Museum exhibits, los angeles collections, antiquities, decorative arts, sculpture, manuscripts, photography, paintings, drawings", "thumbimage": "http://www.getty.edu/museum/media/images/web/thumbnail/00323101.jpg", "date": "about 1450", "place_created": "Cologne, Germany", "object_type": "Folio"}