{"maker": "Unknown", "title": "Attic Red-Figure Nicosthenic Cup (and 1 detached fragment)", "description": "Attic Red-Figure Nicosthenic Cup (and 1 detached fragment); Unknown; Athens, Greece; about 520 B.C.; Terracotta; 14.2 x 42.1 x 34.3 cm (5 9/16 x 16 9/16 x 13 1/2 in.); 81.AE.57; Gift of Dr. L. S. Shukla; J. Paul Getty Museum, Los Angeles, California", "on_view": "yes", "open_content": "no", "object_number": "81.AE.57", "canonical_url": "http://www.getty.edu/art/collection/objects/9442", "keywords": "Getty Museum collections, artworks, art works, art history, video, interpretation of art, acquisitions, artists, Getty art, collections Getty, collezioni Getty, colecciones Getty, Sammlung Getty, Getty exhibits, Getty current exhibitions, Getty Museum exhibits, los angeles collections, antiquities, decorative arts, sculpture, manuscripts, photography, paintings, drawings", "name": "Attic Red-Figure Nicosthenic Cup (and 1 detached fragment)", "classification": "Vessels", "culture": "Greek", "date": "about 520 B.C.", "department": "Antiquities", "dimensions": "14.2 x 42.1 x 34.3 cm (5 9/16 x 16 9/16 x 13 1/2 in.)", "place_created": "Athens, Greece", "object_type": "Cup", "medium": "Terracotta"}