{"maker": "Jacques Dubois", "thumbimage": "http://www.getty.edu/museum/media/images/web/thumbnail/00639101.jpg", "title": "Corner Cupboard (Encoignure)", "description": "Corner Cupboard (Encoignure); Jacques Dubois (French, 1694 - 1763, master 1742); Paris, France; about 1755; Oak painted with vernis Martin; gilt bronze mounts; brèche d'Alep top; 97.2 x 80 x 58.7 cm (38 1/4 x 31 1/2 x 23 1/8 in.); 78.DA.119.2; J. Paul Getty Museum, Los Angeles, California", "on_view": "yes", "open_content": "yes", "object_number": "78.DA.119.2", "canonical_url": "http://www.getty.edu/art/collection/objects/5652", "image_full": "http://www.getty.edu/museum/media/images/web/download/00639101.jpg", "keywords": "Getty Museum collections, artworks, art works, art history, video, interpretation of art, acquisitions, artists, Getty art, collections Getty, collezioni Getty, colecciones Getty, Sammlung Getty, Getty exhibits, Getty current exhibitions, Getty Museum exhibits, los angeles collections, antiquities, decorative arts, sculpture, manuscripts, photography, paintings, drawings", "name": "Corner Cupboard (Encoignure)", "classification": "Decorative Arts", "culture": "French", "image": "http://www.getty.edu/museum/media/images/web/enlarge/00639101.jpg", "date": "about 1755", "department": "Sculpture & Decorative Arts", "dimensions": "97.2 x 80 x 58.7 cm (38 1/4 x 31 1/2 x 23 1/8 in.)", "place_created": "Paris, France", "object_type": "Furniture", "medium": "Oak painted with vernis Martin; gilt bronze mounts; brèche d'Alep top"}