{"description": "Attic Red-Figure Cup Fragments (9); Possibly Triptolemos Painter (Greek (Attic), active about 490 - 470 B.C.), Attributed to Makron (Greek (Attic), active about 490 - 480 B.C.), possibly Tarquinia Painter, et al; Athens, Greece; about 490 - 480 B.C.; Terracotta; 81.AE.212; J. Paul Getty Museum, Los Angeles, California", "department": "Antiquities", "name": "Attic Red-Figure Cup Fragments (9)", "object_number": "81.AE.212", "medium": "Terracotta", "object_type": "Cup", "place_created": "Athens, Greece", "maker": "Possibly Triptolemos Painter, Attributed to Makron, possibly Tarquinia Painter, et al", "title": "Attic Red-Figure Cup Fragments (9)", "culture": "Greek (Attic)", "keywords": "Getty Museum collections, artworks, art works, art history, video, interpretation of art, acquisitions, artists, Getty art, collections Getty, collezioni Getty, colecciones Getty, Sammlung Getty, Getty exhibits, Getty current exhibitions, Getty Museum exhibits, los angeles collections, antiquities, decorative arts, sculpture, manuscripts, photography, paintings, drawings", "on_view": "yes", "date": "about 490 - 480 B.C.", "open_content": "no", "classification": "Vessels"}