{"open_content": "yes", "classification": "Paintings", "name": "The Vicomtesse de Vaudreuil", "maker": "Élisabeth Louise Vigée Le Brun", "description": "The Vicomtesse de Vaudreuil; Élisabeth Louise Vigée Le Brun (French, 1755 - 1842); 1785; Oil on panel; 83.2 x 64.8 cm (32 3/4 x 25 1/2 in.); 85.PB.443; J. Paul Getty Museum, Los Angeles, California", "image_full": "http://www.getty.edu/museum/media/images/web/download/00090101.jpg", "dimensions": "83.2 x 64.8 cm (32 3/4 x 25 1/2 in.)", "object_number": "85.PB.443", "title": "The Vicomtesse de Vaudreuil", "department": "Paintings", "image": "http://www.getty.edu/museum/media/images/web/enlarge/00090101.jpg", "culture": "French", "medium": "Oil on panel", "on_view": "yes", "keywords": "Getty Museum collections, artworks, art works, art history, video, interpretation of art, acquisitions, artists, Getty art, collections Getty, collezioni Getty, colecciones Getty, Sammlung Getty, Getty exhibits, Getty current exhibitions, Getty Museum exhibits, los angeles collections, antiquities, decorative arts, sculpture, manuscripts, photography, paintings, drawings", "thumbimage": "http://www.getty.edu/museum/media/images/web/thumbnail/00090101.jpg", "date": "1785", "location": "gc", "object_type": "Painting"}