{"open_content": "yes", "classification": "Manuscripts", "name": "Initial E: Two Soldiers Fighting and a Judge; Initial C: A King Pulling a Man Through a Portal", "maker": "Unknown, Michael Lupi de Çandiu", "description": "Initial E: Two Soldiers Fighting and a Judge; Initial C: A King Pulling a Man Through a Portal; Unknown, Michael Lupi de Çandiu (Spanish, active Pamplona, Spain 1297 - 1305); Northeastern Spain, Spain; about 1290 - 1310; Tempera colors, gold leaf, and ink on parchment; Leaf: 36.5 x 24 cm (14 3/8 x 9 7/16 in.); Ms. Ludwig XIV 6, fol. 129; J. Paul Getty Museum, Los Angeles, California", "image_full": "http://www.getty.edu/museum/media/images/web/download/00515401.jpg", "dimensions": "Leaf: 36.5 x 24 cm (14 3/8 x 9 7/16 in.)", "object_number": "Ms. Ludwig XIV 6, fol. 129", "title": "Initial E: Two Soldiers Fighting and a Judge; Initial C: A King Pulling a Man Through a Portal", "department": "Manuscripts", "image": "http://www.getty.edu/museum/media/images/web/enlarge/00515401.jpg", "culture": "Spanish", "medium": "Tempera colors, gold leaf, and ink on parchment", "on_view": "yes", "keywords": "Getty Museum collections, artworks, art works, art history, video, interpretation of art, acquisitions, artists, Getty art, collections Getty, collezioni Getty, colecciones Getty, Sammlung Getty, Getty exhibits, Getty current exhibitions, Getty Museum exhibits, los angeles collections, antiquities, decorative arts, sculpture, manuscripts, photography, paintings, drawings", "thumbimage": "http://www.getty.edu/museum/media/images/web/thumbnail/00515401.jpg", "date": "about 1290 - 1310", "place_created": "Northeastern Spain, Spain", "object_type": "Folio"}