{"description": "Mycenaean Stirrup Jar; Unknown; Greece; about 1300 B.C.; Terracotta; 8 × 10.5 cm (3 1/8 × 4 1/8 in.); 81.AE.61.2; J. Paul Getty Museum, Los Angeles, California", "dimensions": "8 × 10.5 cm (3 1/8 × 4 1/8 in.)", "department": "Antiquities", "name": "Mycenaean Stirrup Jar", "object_number": "81.AE.61.2", "medium": "Terracotta", "object_type": "Jar", "title": "Mycenaean Stirrup Jar", "maker": "Unknown", "place_created": "Greece", "culture": "Greek (Mycenaean)", "keywords": "Getty Museum collections, artworks, art works, art history, video, interpretation of art, acquisitions, artists, Getty art, collections Getty, collezioni Getty, colecciones Getty, Sammlung Getty, Getty exhibits, Getty current exhibitions, Getty Museum exhibits, los angeles collections, antiquities, decorative arts, sculpture, manuscripts, photography, paintings, drawings", "on_view": "yes", "date": "about 1300 B.C.", "open_content": "no", "classification": "Vessels"}