{"maker": "Unknown", "title": "Stater", "on_view": "yes", "open_content": "no", "object_number": "80.NB.68.1", "canonical_url": "http://www.getty.edu/art/collection/objects/9230", "keywords": "Getty Museum collections, artworks, art works, art history, video, interpretation of art, acquisitions, artists, Getty art, collections Getty, collezioni Getty, colecciones Getty, Sammlung Getty, Getty exhibits, Getty current exhibitions, Getty Museum exhibits, los angeles collections, antiquities, decorative arts, sculpture, manuscripts, photography, paintings, drawings", "name": "Stater", "classification": "Coins", "culture": "Greek (Elian)", "date": "about 400 B.C.", "department": "Antiquities", "description": "Stater; Unknown; Olympia, Greece; about 400 B.C.; Silver; 80.NB.68.1; J. Paul Getty Museum, Los Angeles, California", "place_created": "Olympia, Greece", "object_type": "Coin", "medium": "Silver"}