{"open_content": "yes", "classification": "Sculpture", "name": "Statuette of a Seated Goddess", "maker": "Unknown", "description": "Statuette of a Seated Goddess; Unknown; South Italy; 3rd century B.C.; Terracotta with polychromy; 4.5 cm (1 3/4 in.); 71.AD.345; J. Paul Getty Museum, Los Angeles, California", "image_full": "http://www.getty.edu/museum/media/images/web/download/00788901.jpg", "dimensions": "4.5 cm (1 3/4 in.)", "object_number": "71.AD.345", "title": "Statuette of a Seated Goddess", "department": "Antiquities", "image": "http://www.getty.edu/museum/media/images/web/enlarge/00788901.jpg", "culture": "Greek (South Italian)", "medium": "Terracotta with polychromy", "on_view": "yes", "keywords": "Getty Museum collections, artworks, art works, art history, video, interpretation of art, acquisitions, artists, Getty art, collections Getty, collezioni Getty, colecciones Getty, Sammlung Getty, Getty exhibits, Getty current exhibitions, Getty Museum exhibits, los angeles collections, antiquities, decorative arts, sculpture, manuscripts, photography, paintings, drawings", "thumbimage": "http://www.getty.edu/museum/media/images/web/thumbnail/00788901.jpg", "date": "3rd century B.C.", "place_created": "South Italy", "object_type": "Female figure"}