{"description": "Snake Bracelet; Unknown; Egypt; 3rd - 2nd century B.C.; Gold, glass; 7.2 cm (2 13/16 in.); 84.AM.849; J. Paul Getty Museum, Los Angeles, California", "dimensions": "7.2 cm (2 13/16 in.)", "department": "Antiquities", "name": "Snake Bracelet", "object_number": "84.AM.849", "medium": "Gold, glass", "object_type": "Bracelet", "location": "gv", "title": "Snake Bracelet", "maker": "Unknown", "image": "http://www.getty.edu/museum/media/images/web/enlarge/01286601.jpg", "place_created": "Egypt", "image_full": "http://www.getty.edu/museum/media/images/web/download/01286601.jpg", "culture": "Romano-Egyptian", "keywords": "Getty Museum collections, artworks, art works, art history, video, interpretation of art, acquisitions, artists, Getty art, collections Getty, collezioni Getty, colecciones Getty, Sammlung Getty, Getty exhibits, Getty current exhibitions, Getty Museum exhibits, los angeles collections, antiquities, decorative arts, sculpture, manuscripts, photography, paintings, drawings", "thumbimage": "http://www.getty.edu/museum/media/images/web/thumbnail/01286601.jpg", "on_view": "yes", "date": "3rd - 2nd century B.C.", "open_content": "yes", "classification": "Jewelry"}