{"description": "Colossal Head of a Ruler; Unknown; Egypt; 1st century B.C.; Limestone; 61 x 40.7 x 42 cm (24 x 16 x 16 9/16 in.); 83.AA.254; Gift of Vasek Polak; J. Paul Getty Museum, Los Angeles, California", "dimensions": "61 x 40.7 x 42 cm (24 x 16 x 16 9/16 in.)", "department": "Antiquities", "name": "Colossal Head of a Ruler", "object_number": "83.AA.254", "medium": "Limestone", "object_type": "Male portrait", "title": "Colossal Head of a Ruler", "maker": "Unknown", "place_created": "Egypt", "culture": "Greco-Roman", "keywords": "Getty Museum collections, artworks, art works, art history, video, interpretation of art, acquisitions, artists, Getty art, collections Getty, collezioni Getty, colecciones Getty, Sammlung Getty, Getty exhibits, Getty current exhibitions, Getty Museum exhibits, los angeles collections, antiquities, decorative arts, sculpture, manuscripts, photography, paintings, drawings", "on_view": "yes", "date": "1st century B.C.", "open_content": "no", "classification": "Sculpture"}