{"description": "Hemispherical Cup; Unknown; Eastern Parthian Empire; 1st century B.C.; Gilt silver and garnets; 5.7 × 10.2 cm (2 1/4 × 4 in.); 86.AM.754.2; J. Paul Getty Museum, Los Angeles, California", "dimensions": "5.7 × 10.2 cm (2 1/4 × 4 in.)", "department": "Antiquities", "name": "Hemispherical Cup", "object_number": "86.AM.754.2", "medium": "Gilt silver and garnets", "object_type": "Cup", "location": "gv", "title": "Hemispherical Cup", "maker": "Unknown", "image": "http://www.getty.edu/museum/media/images/web/enlarge/01497001.jpg", "place_created": "Eastern Parthian Empire", "image_full": "http://www.getty.edu/museum/media/images/web/download/01497001.jpg", "culture": "Near Eastern (Parthian)", "keywords": "Getty Museum collections, artworks, art works, art history, video, interpretation of art, acquisitions, artists, Getty art, collections Getty, collezioni Getty, colecciones Getty, Sammlung Getty, Getty exhibits, Getty current exhibitions, Getty Museum exhibits, los angeles collections, antiquities, decorative arts, sculpture, manuscripts, photography, paintings, drawings", "thumbimage": "http://www.getty.edu/museum/media/images/web/thumbnail/01497001.jpg", "on_view": "yes", "date": "1st century B.C.", "open_content": "yes", "classification": "Vessels"}