{"description": "Corinthian Alabastron; Unknown; Greece (Corinth); about 620 - 590 B.C.; Terracotta; 8.9 × 4.8 cm (3 1/2 × 1 7/8 in.); 86.AE.43; J. Paul Getty Museum, Los Angeles, California", "dimensions": "8.9 × 4.8 cm (3 1/2 × 1 7/8 in.)", "department": "Antiquities", "name": "Corinthian Alabastron", "object_number": "86.AE.43", "medium": "Terracotta", "object_type": "Alabastron", "title": "Corinthian Alabastron", "maker": "Unknown", "image": "http://www.getty.edu/museum/media/images/web/enlarge/01375601.jpg", "place_created": "Greece (Corinth)", "image_full": "http://www.getty.edu/museum/media/images/web/download/01375601.jpg", "culture": "Greek (Corinthian)", "keywords": "Getty Museum collections, artworks, art works, art history, video, interpretation of art, acquisitions, artists, Getty art, collections Getty, collezioni Getty, colecciones Getty, Sammlung Getty, Getty exhibits, Getty current exhibitions, Getty Museum exhibits, los angeles collections, antiquities, decorative arts, sculpture, manuscripts, photography, paintings, drawings", "thumbimage": "http://www.getty.edu/museum/media/images/web/thumbnail/01375601.jpg", "on_view": "yes", "date": "about 620 - 590 B.C.", "open_content": "yes", "classification": "Vessels"}