{"description": "Pair of Altars with Relief Decoration; Unknown; Calabria, Italy; first quarter of 4th century B.C.; Terracotta; 86.AD.598; J. Paul Getty Museum, Los Angeles, California", "department": "Antiquities", "name": "Pair of Altars with Relief Decoration", "object_number": "86.AD.598", "medium": "Terracotta", "object_type": "Altar", "location": "gv", "place_created": "Calabria, Italy", "maker": "Unknown", "image": "http://www.getty.edu/museum/media/images/web/enlarge/01526401.jpg", "title": "Pair of Altars with Relief Decoration", "image_full": "http://www.getty.edu/museum/media/images/web/download/01526401.jpg", "culture": "Greek (South Italian)", "keywords": "Getty Museum collections, artworks, art works, art history, video, interpretation of art, acquisitions, artists, Getty art, collections Getty, collezioni Getty, colecciones Getty, Sammlung Getty, Getty exhibits, Getty current exhibitions, Getty Museum exhibits, los angeles collections, antiquities, decorative arts, sculpture, manuscripts, photography, paintings, drawings", "thumbimage": "http://www.getty.edu/museum/media/images/web/thumbnail/01526401.jpg", "on_view": "yes", "date": "first quarter of 4th century B.C.", "open_content": "yes", "classification": "Implements"}