{"canonical_url": "http://www.getty.edu/art/collection/objects/10901", "description": "Belt Buckle and Tongue; Unknown; Britain (?); 2nd - 4th century; Bronze; 3.2 × 5.2 cm (1 1/4 × 2 in.); 84.AC.740; Gift of Vasek Polak; J. Paul Getty Museum, Los Angeles, California", "keywords": "Getty Museum collections, artworks, art works, art history, video, interpretation of art, acquisitions, artists, Getty art, collections Getty, collezioni Getty, colecciones Getty, Sammlung Getty, Getty exhibits, Getty current exhibitions, Getty Museum exhibits, los angeles collections, antiquities, decorative arts, sculpture, manuscripts, photography, paintings, drawings", "title": "Belt Buckle and Tongue", "name": "Belt Buckle and Tongue", "culture": "Roman", "medium": "Bronze", "date": "2nd - 4th century", "dimensions": "3.2 × 5.2 cm (1 1/4 × 2 in.)", "maker": "Unknown", "place_created": "Britain (?)", "object_type": "Buckle", "object_number": "84.AC.740", "open_content": "no", "on_view": "no"}