{"canonical_url": "http://www.getty.edu/art/collection/objects/10384", "description": "Group of Armor for Horses: Prometodpidia (2) and Breastplates (2); Unknown; South Italy; about 480 B.C.; Bronze, amber, ivory; 83.AC.7; J. Paul Getty Museum, Los Angeles, California", "keywords": "Getty Museum collections, artworks, art works, art history, video, interpretation of art, acquisitions, artists, Getty art, collections Getty, collezioni Getty, colecciones Getty, Sammlung Getty, Getty exhibits, Getty current exhibitions, Getty Museum exhibits, los angeles collections, antiquities, decorative arts, sculpture, manuscripts, photography, paintings, drawings", "title": "Group of Armor for Horses: Prometodpidia (2) and Breastplates (2)", "name": "Group of Armor for Horses: Prometodpidia (2) and Breastplates (2)", "culture": "South Italian", "medium": "Bronze, amber, ivory", "date": "about 480 B.C.", "maker": "Unknown", "place_created": "South Italy", "object_type": "Horse trapping", "object_number": "83.AC.7", "image": "http://www.getty.edu/museum/media/images/web/enlarge/01232601.jpg", "thumbimage": "http://www.getty.edu/museum/media/images/web/thumbnail/01232601.jpg", "open_content": "yes", "on_view": "no", "image_full": "http://www.getty.edu/museum/media/images/web/download/01232601.jpg"}