{"description": "Attic Geometric Two-handled Cup; Unknown; Greece; about 900 B.C.; Terracotta; 5.2 x 8 cm (2 1/16 x 3 1/8 in.); 82.AE.56.9; J. Paul Getty Museum, Los Angeles, California", "dimensions": "5.2 x 8 cm (2 1/16 x 3 1/8 in.)", "department": "Antiquities", "name": "Attic Geometric Two-handled Cup", "object_number": "82.AE.56.9", "medium": "Terracotta", "object_type": "Cup", "title": "Attic Geometric Two-handled Cup", "maker": "Unknown", "place_created": "Greece", "culture": "Greek (Attic)", "keywords": "Getty Museum collections, artworks, art works, art history, video, interpretation of art, acquisitions, artists, Getty art, collections Getty, collezioni Getty, colecciones Getty, Sammlung Getty, Getty exhibits, Getty current exhibitions, Getty Museum exhibits, los angeles collections, antiquities, decorative arts, sculpture, manuscripts, photography, paintings, drawings", "on_view": "yes", "date": "about 900 B.C.", "open_content": "no", "classification": "Vessels"}