{"maker": "Unknown", "title": "Stater", "description": "Stater; Unknown; Tarentum (Taras), South Italy; 380 - 345 B.C.; Silver; 0.0068 kg (0.015 lb.); 82.NB.118.2; J. Paul Getty Museum, Los Angeles, California", "on_view": "yes", "open_content": "no", "object_number": "82.NB.118.2", "canonical_url": "http://www.getty.edu/art/collection/objects/10306", "keywords": "Getty Museum collections, artworks, art works, art history, video, interpretation of art, acquisitions, artists, Getty art, collections Getty, collezioni Getty, colecciones Getty, Sammlung Getty, Getty exhibits, Getty current exhibitions, Getty Museum exhibits, los angeles collections, antiquities, decorative arts, sculpture, manuscripts, photography, paintings, drawings", "name": "Stater", "classification": "Coins", "culture": "Greek (South Italian, Tarantine)", "date": "380 - 345 B.C.", "department": "Antiquities", "dimensions": "0.0068 kg (0.015 lb.)", "place_created": "Tarentum (Taras), South Italy", "object_type": "Coin", "medium": "Silver"}