{"canonical_url": "http://www.getty.edu/art/collection/objects/10790", "description": "Head of Socrates (on Eighteenth-Century Bust); Unknown; 1st century; 11.4 cm (4 1/2 in.); 83.AA.426; Gift of Max Falk; J. Paul Getty Museum, Los Angeles, California", "keywords": "Getty Museum collections, artworks, art works, art history, video, interpretation of art, acquisitions, artists, Getty art, collections Getty, collezioni Getty, colecciones Getty, Sammlung Getty, Getty exhibits, Getty current exhibitions, Getty Museum exhibits, los angeles collections, antiquities, decorative arts, sculpture, manuscripts, photography, paintings, drawings", "title": "Head of Socrates (on Eighteenth-Century Bust)", "name": "Head of Socrates (on Eighteenth-Century Bust)", "culture": "Roman", "date": "1st century", "dimensions": "11.4 cm (4 1/2 in.)", "maker": "Unknown", "object_type": "Male portrait", "object_number": "83.AA.426", "open_content": "no", "on_view": "no"}