{"description": "Seal or Stamp; Unknown; South Italy; 5th century B.C. or later; Bronze; 3.3 cm (1 5/16 in.); 78.AC.381.59; Gift of Herbert L. Lucas; J. Paul Getty Museum, Los Angeles, California", "dimensions": "3.3 cm (1 5/16 in.)", "department": "Antiquities", "name": "Seal or Stamp", "object_number": "78.AC.381.59", "medium": "Bronze", "object_type": "Seal-stamp", "title": "Seal or Stamp", "maker": "Unknown", "place_created": "South Italy", "culture": "Greek (?)", "keywords": "Getty Museum collections, artworks, art works, art history, video, interpretation of art, acquisitions, artists, Getty art, collections Getty, collezioni Getty, colecciones Getty, Sammlung Getty, Getty exhibits, Getty current exhibitions, Getty Museum exhibits, los angeles collections, antiquities, decorative arts, sculpture, manuscripts, photography, paintings, drawings", "on_view": "yes", "date": "5th century B.C. or later", "open_content": "no", "classification": "Implements"}