{"description": "Fragment of an Arcade Sarcophagus; Unknown; Rome, Lazio, Italy; late 3rd century; Asia Minor marble; 95.5 × 114 cm (37 5/8 × 44 7/8 in.); 78.AA.352.1; Gift of Marshall and Ruth Goldberg; J. Paul Getty Museum, Los Angeles, California", "dimensions": "95.5 × 114 cm (37 5/8 × 44 7/8 in.)", "department": "Antiquities", "name": "Fragment of an Arcade Sarcophagus", "object_number": "78.AA.352.1", "medium": "Asia Minor marble", "object_type": "Sarcophagus", "title": "Fragment of an Arcade Sarcophagus", "maker": "Unknown", "place_created": "Rome, Lazio, Italy", "culture": "Roman", "keywords": "Getty Museum collections, artworks, art works, art history, video, interpretation of art, acquisitions, artists, Getty art, collections Getty, collezioni Getty, colecciones Getty, Sammlung Getty, Getty exhibits, Getty current exhibitions, Getty Museum exhibits, los angeles collections, antiquities, decorative arts, sculpture, manuscripts, photography, paintings, drawings", "on_view": "yes", "date": "late 3rd century", "open_content": "no", "classification": "Sculpture"}