{"canonical_url": "http://www.getty.edu/art/collection/objects/10882", "description": "Torso of a Male Statue; Unknown; Rome, Lazio, Italy; 1st century; Marble; 51.5 cm (20 1/4 in.); 84.AA.28; Gift of Dr. Max Gerchik; J. Paul Getty Museum, Los Angeles, California", "keywords": "Getty Museum collections, artworks, art works, art history, video, interpretation of art, acquisitions, artists, Getty art, collections Getty, collezioni Getty, colecciones Getty, Sammlung Getty, Getty exhibits, Getty current exhibitions, Getty Museum exhibits, los angeles collections, antiquities, decorative arts, sculpture, manuscripts, photography, paintings, drawings", "title": "Torso of a Male Statue", "name": "Torso of a Male Statue", "culture": "Roman", "medium": "Marble", "date": "1st century", "dimensions": "51.5 cm (20 1/4 in.)", "maker": "Unknown", "place_created": "Rome, Lazio, Italy", "object_type": "Male figure", "object_number": "84.AA.28", "open_content": "no", "on_view": "no"}