{"canonical_url": "http://www.getty.edu/art/collection/objects/11157", "description": "Engraved Gem; Unknown; Roman Empire; 1st century B.C.; Carnelian; 1.4 × 1 × 0.3 cm (9/16 × 3/8 × 1/8 in.); 85.AN.370.67; J. Paul Getty Museum, Los Angeles, California", "keywords": "Getty Museum collections, artworks, art works, art history, video, interpretation of art, acquisitions, artists, Getty art, collections Getty, collezioni Getty, colecciones Getty, Sammlung Getty, Getty exhibits, Getty current exhibitions, Getty Museum exhibits, los angeles collections, antiquities, decorative arts, sculpture, manuscripts, photography, paintings, drawings", "title": "Engraved Gem", "name": "Engraved Gem", "culture": "Roman", "medium": "Carnelian", "date": "1st century B.C.", "dimensions": "1.4 × 1 × 0.3 cm (9/16 × 3/8 × 1/8 in.)", "maker": "Unknown", "place_created": "Roman Empire", "object_type": "Gem", "object_number": "85.AN.370.67", "image": "http://www.getty.edu/museum/media/images/web/enlarge/01316301.jpg", "thumbimage": "http://www.getty.edu/museum/media/images/web/thumbnail/01316301.jpg", "open_content": "yes", "on_view": "no", "image_full": "http://www.getty.edu/museum/media/images/web/download/01316301.jpg"}