{"description": "Attic Red-Figure Kylix Fragment; Attributed to Douris (Greek (Attic), active 500 - 460 B.C.); Athens, Greece; about 490 B.C.; Terracotta; 4.2 × 2.8 cm (1 5/8 × 1 1/16 in.); 87.AE.153; Gift of Dietrich von Bothmer; J. Paul Getty Museum, Los Angeles, California", "dimensions": "4.2 × 2.8 cm (1 5/8 × 1 1/16 in.)", "department": "Antiquities", "name": "Attic Red-Figure Kylix Fragment", "object_number": "87.AE.153", "medium": "Terracotta", "object_type": "Cup", "title": "Attic Red-Figure Kylix Fragment", "maker": "Attributed to Douris", "place_created": "Athens, Greece", "culture": "Greek (Attic)", "keywords": "Getty Museum collections, artworks, art works, art history, video, interpretation of art, acquisitions, artists, Getty art, collections Getty, collezioni Getty, colecciones Getty, Sammlung Getty, Getty exhibits, Getty current exhibitions, Getty Museum exhibits, los angeles collections, antiquities, decorative arts, sculpture, manuscripts, photography, paintings, drawings", "on_view": "yes", "date": "about 490 B.C.", "open_content": "no", "classification": "Vessels"}