{"description": "Fragment of a Mosaic Glass Vessel; Unknown; Italy; 1st century B.C. - 1st century A.D.; Glass; 3.4 x 2.9 cm (1 5/16 x 1 1/8 in.); 83.AF.28.21; J. Paul Getty Museum, Los Angeles, California", "dimensions": "3.4 x 2.9 cm (1 5/16 x 1 1/8 in.)", "department": "Antiquities", "name": "Fragment of a Mosaic Glass Vessel", "object_number": "83.AF.28.21", "medium": "Glass", "object_type": "Bowl", "title": "Fragment of a Mosaic Glass Vessel", "maker": "Unknown", "place_created": "Italy", "culture": "Roman", "keywords": "Getty Museum collections, artworks, art works, art history, video, interpretation of art, acquisitions, artists, Getty art, collections Getty, collezioni Getty, colecciones Getty, Sammlung Getty, Getty exhibits, Getty current exhibitions, Getty Museum exhibits, los angeles collections, antiquities, decorative arts, sculpture, manuscripts, photography, paintings, drawings", "on_view": "yes", "date": "1st century B.C. - 1st century A.D.", "open_content": "no", "classification": "Vessels"}